azurefunctions/extensions/base/__init__.py
azurefunctions/extensions/base/grpcClientType.py
azurefunctions/extensions/base/meta.py
azurefunctions/extensions/base/sdkType.py
azurefunctions/extensions/base/utils.py
azurefunctions/extensions/base/web.py
durable_agent_framework-0.0.0.dev0.dist-info/licenses/LICENSE
durable_agent_framework-0.0.0.dev0.dist-info/METADATA
durable_agent_framework-0.0.0.dev0.dist-info/WHEEL
durable_agent_framework-0.0.0.dev0.dist-info/top_level.txt
durable_agent_framework-0.0.0.dev0.dist-info/RECORD
